fastAIcourse/__init__.py
fastAIcourse/_modidx.py
fastAIcourse/automate.py
fastAIcourse/deployment.py
fastAIcourse/functions.py
fastAIcourse/intro.py
fastAIcourse/neuralnet.py
fastAIcourse-0.0.60.dist-info/LICENSE
fastAIcourse-0.0.60.dist-info/METADATA
fastAIcourse-0.0.60.dist-info/WHEEL
fastAIcourse-0.0.60.dist-info/entry_points.txt
fastAIcourse-0.0.60.dist-info/top_level.txt
fastAIcourse-0.0.60.dist-info/RECORD
