Metadata-Version: 2.1
Name: fastAIcourse
Version: 0.0.60
Summary: fastAIcourse
Home-page: https://github.com/bthek1/fastAIcourse
Author: Benedict Thekkel
Author-email: bthekkel1@gmail.com
License: Apache Software License 2.0
Keywords: nbdev jupyter notebook python
Classifier: Development Status :: 4 - Beta
Classifier: Intended Audience :: Developers
Classifier: Natural Language :: English
Classifier: Programming Language :: Python :: 3.7
Classifier: Programming Language :: Python :: 3.8
Classifier: Programming Language :: Python :: 3.9
Classifier: Programming Language :: Python :: 3.10
Classifier: License :: OSI Approved :: Apache Software License
Requires-Python: >=3.7
License-File: LICENSE
Requires-Dist: fastdownload <2,>=0.0.5
Requires-Dist: fastcore <1.6,>=1.5.29
Requires-Dist: torchvision
Requires-Dist: matplotlib
Requires-Dist: pandas
Requires-Dist: requests
Requires-Dist: pyyaml
Requires-Dist: fastprogress >=0.2.4
Requires-Dist: pillow >6.0.0
Requires-Dist: scikit-learn
Requires-Dist: scipy
Requires-Dist: spacy <4
Requires-Dist: packaging
Requires-Dist: fastbook
Requires-Dist: numba
Requires-Dist: kaggle
Requires-Dist: seaborn
Requires-Dist: dtreeviz
Requires-Dist: diffusers
Provides-Extra: dev
Requires-Dist: ipywidgets ; extra == 'dev'
Requires-Dist: pytorch-lightning ; extra == 'dev'
Requires-Dist: pytorch-ignite ; extra == 'dev'
Requires-Dist: transformers ; extra == 'dev'
Requires-Dist: sentencepiece ; extra == 'dev'
Requires-Dist: tensorboard ; extra == 'dev'
Requires-Dist: pydicom ; extra == 'dev'
Requires-Dist: catalyst ; extra == 'dev'
Requires-Dist: flask-compress ; extra == 'dev'
Requires-Dist: captum >=0.3 ; extra == 'dev'
Requires-Dist: flask ; extra == 'dev'
Requires-Dist: wandb ; extra == 'dev'
Requires-Dist: kornia ; extra == 'dev'
Requires-Dist: scikit-image ; extra == 'dev'
Requires-Dist: neptune-client ; extra == 'dev'
Requires-Dist: comet-ml ; extra == 'dev'
Requires-Dist: albumentations ; extra == 'dev'
Requires-Dist: opencv-python ; extra == 'dev'
Requires-Dist: pyarrow ; extra == 'dev'
Requires-Dist: ninja ; extra == 'dev'
Requires-Dist: timm >=0.6.2.dev ; extra == 'dev'
Requires-Dist: accelerate >=0.10.0 ; extra == 'dev'
